train_12306_mcp/__init__.py
train_12306_mcp/__main__.py
train_12306_mcp/common_define.py
train_12306_mcp/common_func.py
train_12306_mcp/server.py
train_12306_mcp-0.1.3.dist-info/METADATA
train_12306_mcp-0.1.3.dist-info/WHEEL
train_12306_mcp-0.1.3.dist-info/entry_points.txt
train_12306_mcp-0.1.3.dist-info/RECORD
