Metadata-Version: 2.4
Name: train_12306_mcp
Version: 0.1.3
Summary: train_12306_mcp
Requires-Python: >=3.10
Requires-Dist: build>=1.3.0
Requires-Dist: fake-useragent>=2.2.0
Requires-Dist: fastmcp>=2.12.4
Requires-Dist: pip>=25.2
Requires-Dist: python-dateutil>=2.9.0.post0
Requires-Dist: setuptools>=80.9.0
Requires-Dist: twine>=6.2.0
